pyaez/BioMassCalc.py
pyaez/ClimateRegime.py
pyaez/ClimaticConstraints.py
pyaez/CropSimulation.py
pyaez/CropWatCalc.py
pyaez/ETOCalc.py
pyaez/EconomicSuitability.py
pyaez/LGPCalc.py
pyaez/SoilConstraints.py
pyaez/TerrainConstraints.py
pyaez/ThermalScreening.py
pyaez/UtilitiesCalc.py
pyaez/__init__.py
pyaez/__version__.py
PyAEZ-2.2.dist-info/LICENSE
PyAEZ-2.2.dist-info/METADATA
PyAEZ-2.2.dist-info/WHEEL
PyAEZ-2.2.dist-info/top_level.txt
PyAEZ-2.2.dist-info/RECORD
