Metadata-Version: 2.1
Name: PyAEZ
Version: 2.2
Summary: PyAEZ is a python package consisted of many algorithms related to Agro-ecalogical zoning (AEZ) framework.
Home-page: https://github.com/gicait/PyAEZ
Author: Geoinformatics Center, Asian Institute of Technology, Thailand
Author-email: geoinfo@ait.asia
License: MIT License
Keywords: AEZ,Python,Agro-ecological Zoning,Climate Regime,Crop Simulations,Climate Constraints,Soil Constraints,Terrain Constraints,Economic Suitability Analysis,Utility Calculation,Biomass Calculations,Evapotranspiration Calculation,CropWat calculations
Classifier: Programming Language :: Python :: 3
Classifier: Intended Audience :: Developers
Classifier: Intended Audience :: Science/Research
Classifier: License :: OSI Approved :: MIT License
Classifier: Operating System :: OS Independent
Requires-Python: >=3.6
License-File: LICENSE
Requires-Dist: numpy
Requires-Dist: pandas
Requires-Dist: scipy
Requires-Dist: gdal
Requires-Dist: numba
Provides-Extra: dev
Requires-Dist: pytest ; extra == 'dev'
Requires-Dist: black ; extra == 'dev'
Requires-Dist: flake8 ; extra == 'dev'
Requires-Dist: sphinx >=1.7 ; extra == 'dev'
Requires-Dist: pre-commit ; extra == 'dev'
